mcp_alchemy/__init__.py
mcp_alchemy/server.py
mcp_alchemy-2025.8.15.91819.dist-info/METADATA
mcp_alchemy-2025.8.15.91819.dist-info/WHEEL
mcp_alchemy-2025.8.15.91819.dist-info/entry_points.txt
mcp_alchemy-2025.8.15.91819.dist-info/licenses/LICENSE
mcp_alchemy-2025.8.15.91819.dist-info/RECORD
