Metadata-Version: 2.4
Name: mcp-alchemy
Version: 2025.8.15.91819
Summary: A MCP server that connects to your database
Project-URL: Homepage, https://github.com/runekaagaard/mcp-alchemy
Project-URL: Issues, https://github.com/runekaagaard/mcp-alchemy/issues
Project-URL: Disussions, https://github.com/runekaagaard/mcp-alchemy/discussions
Author: Rune Kaagaard
License-File: LICENSE
Classifier: Operating System :: OS Independent
Classifier: Programming Language :: Python :: 3
Requires-Python: >=3.10
Requires-Dist: mcp[cli]>=1.2.0rc1
Requires-Dist: sqlalchemy>=2.0.36
